KolejkaJudge-0.1.202312110937-nspkg.pth
kolejka/judge/__init__.py
kolejka/judge/__nonpath__.py
kolejka/judge/checking.py
kolejka/judge/config.py
kolejka/judge/ctxyaml.py
kolejka/judge/exceptions.py
kolejka/judge/judge.py
kolejka/judge/limits.py
kolejka/judge/parse.py
kolejka/judge/paths.py
kolejka/judge/result.py
kolejka/judge/satori.py
kolejka/judge/task.py
kolejka/judge/typing.py
kolejka/judge/validators.py
kolejka/judge/commands/__init__.py
kolejka/judge/commands/__nonpath__.py
kolejka/judge/commands/base.py
kolejka/judge/commands/check.py
kolejka/judge/commands/compress.py
kolejka/judge/commands/extract.py
kolejka/judge/commands/make.py
kolejka/judge/commands/postgres.py
kolejka/judge/commands/system.py
kolejka/judge/commands/compile/__init__.py
kolejka/judge/commands/compile/__nonpath__.py
kolejka/judge/commands/compile/base.py
kolejka/judge/commands/compile/gcc.py
kolejka/judge/commands/compile/ghc.py
kolejka/judge/commands/compile/mono.py
kolejka/judge/commands/compile/nasm.py
kolejka/judge/commands/compile/nvcc.py
kolejka/judge/systems/__init__.py
kolejka/judge/systems/__nonpath__.py
kolejka/judge/systems/base.py
kolejka/judge/systems/local.py
kolejka/judge/systems/observer.py
kolejka/judge/tasks/__init__.py
kolejka/judge/tasks/__nonpath__.py
kolejka/judge/tasks/background.py
kolejka/judge/tasks/base.py
kolejka/judge/tasks/check.py
kolejka/judge/tasks/cuda.py
kolejka/judge/tasks/io.py
kolejka/judge/tasks/java.py
kolejka/judge/tasks/logs.py
kolejka/judge/tasks/postgres.py
kolejka/judge/tasks/prepare.py
kolejka/judge/tasks/rules.py
kolejka/judge/tasks/run.py
kolejka/judge/tasks/shared.py
kolejka/judge/tasks/system.py
kolejka/judge/tasks/tools.py
kolejka/judge/tasks/workspace.py
kolejka/judge/tasks/build/__init__.py
kolejka/judge/tasks/build/__nonpath__.py
kolejka/judge/tasks/build/auto.py
kolejka/judge/tasks/build/base.py
kolejka/judge/tasks/build/compile.py
kolejka/judge/tasks/build/make.py
kolejka/judge/tasks/build/script.py
KolejkaJudge-0.1.202312110937.dist-info/METADATA
KolejkaJudge-0.1.202312110937.dist-info/WHEEL
KolejkaJudge-0.1.202312110937.dist-info/entry_points.txt
KolejkaJudge-0.1.202312110937.dist-info/namespace_packages.txt
KolejkaJudge-0.1.202312110937.dist-info/top_level.txt
KolejkaJudge-0.1.202312110937.dist-info/RECORD
