Metadata-Version: 2.1
Name: KolejkaJudge
Version: 0.1.202312110937
Summary: Kolejka Satori Judge
Home-page: https://github.com/kolejka/kolejka-judge
Author: KOLEJKA JUDGE
Author-email: kolejka@matinf.uj.edu.pl
License: MIT
Platform: UNKNOWN
Requires-Python: >=3.7
Requires-Dist: KolejkaClient
Requires-Dist: KolejkaCommon
Requires-Dist: pyyaml
Requires-Dist: setproctitle
